eralchemy_schemadisplay_magic/__init__.py
eralchemy_schemadisplay_magic/eralchemy_api.py
eralchemy_schemadisplay_magic/schemadisplay.py
erlachemy_schemadisplay_anywidget_magic-0.0.2.dist-info/LICENSE
erlachemy_schemadisplay_anywidget_magic-0.0.2.dist-info/METADATA
erlachemy_schemadisplay_anywidget_magic-0.0.2.dist-info/WHEEL
erlachemy_schemadisplay_anywidget_magic-0.0.2.dist-info/top_level.txt
erlachemy_schemadisplay_anywidget_magic-0.0.2.dist-info/RECORD
