Metadata-Version: 2.2
Name: erlachemy_schemadisplay_anywidget_magic
Version: 0.0.2
Summary: Python package installation for erlachemy_schemadisplay_anywidget_magicy
Home-page: https://github.com/innovationOUtside/erlachemy_schemadisplay_anywidget_magic
Author: Tony Hirst
Author-email: tony.hirst@open.ac.uk
License: MIT
License-File: LICENSE
Dynamic: author
Dynamic: author-email
Dynamic: description
Dynamic: description-content-type
Dynamic: home-page
Dynamic: license
Dynamic: summary
